cameramodels/__init__.py
cameramodels/align.py
cameramodels/math.py
cameramodels/pinhole_camera.py
cameramodels/rgbd_camera.py
cameramodels/stereo_camera.py
cameramodels/apps/__init__.py
cameramodels/apps/resize_camera_info.py
cameramodels/calib/__init__.py
cameramodels/calib/linear.py
cameramodels/data/__init__.py
cameramodels/data/kinect_v2/camera_info.yaml
cameramodels/data/kinect_v2/hd.jpg
cameramodels/io/__init__.py
cameramodels/io/honnotate.py
cameramodels/models/__init__.py
cameramodels/models/azure_kinect.py
cameramodels/models/d415.py
cameramodels/models/d435.py
cameramodels/models/kinect_v2.py
cameramodels/models/xtion.py
tests/__init__.py
tests/test_align.py
tests/test_models.py
tests/test_pinhole_camera.py
tests/data/__init__.py
tests/data/test_data.py
tests/io/__init__.py
tests/io/test_honnotate.py
cameramodels-0.2.13.dist-info/LICENSE
cameramodels-0.2.13.dist-info/METADATA
cameramodels-0.2.13.dist-info/WHEEL
cameramodels-0.2.13.dist-info/entry_points.txt
cameramodels-0.2.13.dist-info/top_level.txt
cameramodels-0.2.13.dist-info/RECORD
