Metadata-Version: 2.1
Name: cameramodels
Version: 0.2.13
Summary: A python library for cameramodels
Home-page: https://github.com/iory/cameramodels
Author: iory
Author-email: ab.ioryz@gmail.com
License: MIT
Classifier: Development Status :: 5 - Production/Stable
Classifier: Intended Audience :: Developers
Classifier: Natural Language :: English
Classifier: License :: OSI Approved :: MIT License
Classifier: Programming Language :: Python
Classifier: Programming Language :: Python :: 3.5
Classifier: Programming Language :: Python :: 3.6
Classifier: Programming Language :: Python :: 3.7
Classifier: Programming Language :: Python :: Implementation :: CPython
License-File: LICENSE
Requires-Dist: numpy
Requires-Dist: pillow
Requires-Dist: pyyaml
Requires-Dist: scipy
Provides-Extra: all
Requires-Dist: open3d; extra == "all"
Requires-Dist: opencv-python; python_version > "2.7" and extra == "all"
Requires-Dist: opencv-python<=4.2.0.32; python_version <= "2.7" and extra == "all"
